Metadata-Version: 2.1
Name: odoo13-addon-shopinvader-cart-expiry
Version: 13.0.2.0.0
Summary: Shopinvader module to manage an expiry delay on cart
Home-page: http://www.shopinvader.com
Author: ACSONE SA/NV
License: AGPL-3
Platform: UNKNOWN
Classifier: Programming Language :: Python
Classifier: Framework :: Odoo
Classifier: License :: OSI Approved :: GNU Affero General Public License v3
Requires-Python: >=3.5
Requires-Dist: odoo13-addon-queue-job
Requires-Dist: odoo13-addon-shopinvader
Requires-Dist: odoo (<13.1dev,>=13.0a)
